midiroute/__init__.py
midiroute/cli.py
midiroute/main.py
midiroute/midiutils.py
midiroute-0.3.1.dist-info/LICENSE.txt
midiroute-0.3.1.dist-info/METADATA
midiroute-0.3.1.dist-info/WHEEL
midiroute-0.3.1.dist-info/entry_points.txt
midiroute-0.3.1.dist-info/top_level.txt
midiroute-0.3.1.dist-info/RECORD
