Metadata-Version: 2.1
Name: midiroute
Version: 0.3.1
Summary: A command line utility for routing and monitoring MIDI ports.
Home-page: https://github.com/atticave/midiroute
Author: atticave
Author-email: atticave@blueheaps.com
License: UNKNOWN
Keywords: midi interface router monitor diagnostics
Platform: UNKNOWN
Classifier: Development Status :: 3 - Alpha
Classifier: Intended Audience :: Developers
Classifier: Topic :: Multimedia :: Sound/Audio :: Analysis
Classifier: License :: OSI Approved :: MIT License
Classifier: Programming Language :: Python :: 3 :: Only
Classifier: Programming Language :: Python :: 3.7
Classifier: Programming Language :: Python :: 3.8
Classifier: Programming Language :: Python :: 3.9
Requires-Python: >=3.8, <4
Requires-Dist: click
Requires-Dist: mido
Requires-Dist: python-rtmidi
Requires-Dist: tabulate
